{
  "scraper_version": "2.0.7",
  "product_id": "1731593026950104458",
  "title": "BabyBus ふしぎな水塗り絵 くり返し遊べる 汚れない 色鮮やか 持ちやすい ゴム紐付き 可愛いイラスト 知育  ベビーバス ベイビーバス 運筆 知育 2歳 3歳 4歳 ぬりえ",
  "timestamp": "2026-07-05T13:39:54.166Z",
  "type": "product",
  "free_shipping": true,
  "price": {
    "current": "1078",
    "original": "880",
    "discount": "-40%"
  },
  "social_proof": {
    "rating": "4.6",
    "reviews_count": "290",
    "sales_volume": "4.8K sold"
  },
  "seller_info": {
    "name": "BabyBus・ベビーバス"
  },
  "variants": {},
  "marketing_points": [
    "290 global reviews",
    "Photos from reviews",
    "See all photos",
    "gngmirah03",
    "Recommended",
    "Filter by",
    "Includes visuals",
    "Verified purchase",
    "Displaying 290 of 290 reviews",
    "Reset filters",
    "姉弟で楽しく遊んでいます。チビはどうしてもペン先に力が入ってしまって、すでに絵本の表面を削ってしまいました（笑）ペン先もつぶれました(笑)",
    "ピンク＆グリーンセット",
    "2026-05-30",
    "Kualitas cetak: Bagus sangt bagus Kemasan: Bagus Kejernihan isi: Bagus ini sangt bagus untuk ank usia 1thn",
    "2026-06-27",
    "めちゃくちゃ良いです！我が家のダイソンが故障寸前なので買いました。音もダイソンより全然静かだし、何より抜け毛がすごい犬を飼っていて少しカーペットをやっただけでこれだけの毛が収集できました。絶対おすすめ！あとは壊れないことを祈る🙏",
    "2026-01-30",
    "＼水だけで遊べる！くりかえし楽しめる水塗り絵／ Babybusから水で塗るだけで絵が浮かび上がる不思議な塗り絵ブックが登場！ 色が出てくるワクワク体験でおうちでもおでかけ先でも遊べます。 ◆水だけだから安心＆清潔 専用ペンに水を入れてページをなぞるとカラフルなイラストが出現！ インクを使わないから手や服が汚れずママパパも安心。 ◆繰り返し遊べる！ 乾くと色が消えるので何度でも遊べる知育アイテム。 お気に入りのページを何度でも塗って楽しめます。 ◆持ち運びに便利な設計 本体はお子さまの手に持ちやすいサイズ感。 お出かけにもピッタリでどこにでも持っていける！ 便利なペンホルダー付きでペンの紛失防止にも◎ ◆タッチペン対応（※別売り） BabyBusのタッチペン対応にリニューアル！",
    "公式HPからパソコンでデータをダウンロードすればタッチペンでも遊べるようになりました！",
    "※タッチペンは別売りです（はじめてのちいくずかんにのみ付属）",
    "はじめての塗り絵デビューや、ちょっとしたプレゼントにおすすめの1冊です。",
    "※ギフト包装は行っていません。"
  ],
  "source_url": "https://shop.tiktok.com/jp/pdp/babybus-mizu-nurie-kurikaeshi-asoberu-chiiku-yogore-nai-tatchipen-taiou/1731593026950104458?_d=e3m649i12jjb7a&source=product_detail&enter_method=url_semantic_301"
}